{
  "main": {
    "id": "52c40670570e4107",
    "type": "split",
    "children": [
      {
        "id": "246f3b8b5c5cf910",
        "type": "tabs",
        "dimension": 47.12153518123667,
        "children": [
          {
            "id": "e51d1984b30bc0bc",
            "type": "leaf",
            "state": {
              "type": "graph",
              "state": {}
            }
          }
        ]
      },
      {
        "id": "aa3729fb84bbb7b3",
        "type": "tabs",
        "dimension": 52.87846481876333,
        "children": [
          {
            "id": "1d449208d2415f5e",
            "type": "leaf",
            "state": {
              "type": "markdown",
              "state": {
                "file": "python/19_python_package_manager.md",
                "mode": "source",
                "source": false
              }
            }
          }
        ]
      }
    ],
    "direction": "vertical"
  },
  "left": {
    "id": "bdc27f30ec9f48b3",
    "type": "split",
    "children": [
      {
        "id": "587405026c4a139b",
        "type": "tabs",
        "children": [
          {
            "id": "df436ed7dbf124f9",
            "type": "leaf",
            "state": {
              "type": "file-explorer",
              "state": {
                "sortOrder": "alphabetical"
              }
            }
          },
          {
            "id": "141e19c9b3153f7f",
            "type": "leaf",
            "state": {
              "type": "search",
              "state": {
                "query": "",
                "matchingCase": false,
                "explainSearch": false,
                "collapseAll": false,
                "extraContext": false,
                "sortOrder": "alphabetical"
              }
            }
          },
          {
            "id": "ae3cfc8439787b8d",
            "type": "leaf",
            "state": {
              "type": "bookmarks",
              "state": {}
            }
          }
        ]
      }
    ],
    "direction": "horizontal",
    "width": 217.5
  },
  "right": {
    "id": "9e59b0868aa407f0",
    "type": "split",
    "children": [
      {
        "id": "6a6714cc11eef3fb",
        "type": "tabs",
        "children": [
          {
            "id": "2add77b415d188e1",
            "type": "leaf",
            "state": {
              "type": "backlink",
              "state": {
                "file": "python/19_python_package_manager.md",
                "collapseAll": false,
                "extraContext": false,
                "sortOrder": "alphabetical",
                "showSearch": false,
                "searchQuery": "",
                "backlinkCollapsed": false,
                "unlinkedCollapsed": true
              }
            }
          },
          {
            "id": "cf2b44959d09c286",
            "type": "leaf",
            "state": {
              "type": "outgoing-link",
              "state": {
                "file": "python/19_python_package_manager.md",
                "linksCollapsed": false,
                "unlinkedCollapsed": true
              }
            }
          },
          {
            "id": "4aa1ba08e70ad511",
            "type": "leaf",
            "state": {
              "type": "tag",
              "state": {
                "sortOrder": "frequency",
                "useHierarchy": true
              }
            }
          },
          {
            "id": "fe23679320ba14c7",
            "type": "leaf",
            "state": {
              "type": "outline",
              "state": {
                "file": "python/19_python_package_manager.md"
              }
            }
          },
          {
            "id": "5982c9c207dd5227",
            "type": "leaf",
            "state": {
              "type": "calendar",
              "state": {}
            }
          },
          {
            "id": "2a5dc2d3f54085e3",
            "type": "leaf",
            "state": {
              "type": "advanced-tables-toolbar",
              "state": {}
            }
          }
        ],
        "currentTab": 1
      }
    ],
    "direction": "horizontal",
    "width": 300,
    "collapsed": true
  },
  "left-ribbon": {
    "hiddenItems": {
      "switcher:Abrir selector rápido": false,
      "graph:Abrir vista gráfica": false,
      "canvas:Crear nuevo lienzo": false,
      "daily-notes:Abrir la nota de hoy": false,
      "templates:Insertar plantilla": false,
      "command-palette:Abrir paleta de comandos": false,
      "zk-prefixer:Crear nueva nota única": false,
      "table-editor-obsidian:Advanced Tables Toolbar": false
    }
  },
  "active": "1d449208d2415f5e",
  "lastOpenFiles": [
    "python/18_file_handing.md",
    "python/18.1_example.txt",
    "python/17_regular_expressions.md",
    "python/16_exception_handling.md",
    "python/16.1_exercice.md",
    "python/15_python_datetime.md",
    "python/14_python_type_errors.md",
    "python/13_higher_order_functions.md",
    "python/12_list_comprehension.md",
    "python/11_modules.md",
    "python/10_functions.md",
    "python/09_loops.md",
    "python/08_conditionals.md",
    "python/07_dicts.md",
    "python/19.2_creating_a_packages/__pycache__/greet.cpython-310.pyc",
    "python/19.2_creating_a_packages/__pycache__/arithmetic.cpython-310.pyc",
    "python/19.2_creating_a_packages/__pycache__/__init__.cpython-310.pyc",
    "python/__pycache__/countriesss.cpython-310.pyc",
    "python/Modules/seaborn.md",
    "python/Modules/pandas.md",
    "python/Modules/numpy.md",
    "python/Modules/matplotlib.md",
    "python/19.2_creating_a_packages/greet.md",
    "python/19.2_creating_a_packages/arithmetic.md",
    "python/19.2_creating_a_packages/__pycache__",
    "python/19.2_creating_a_packages/__init__.md",
    "python/presidents_data.json",
    "python/countriesss.md",
    "python/__pycache__",
    "python/Modules",
    "python/22_virtual_environment.md",
    "python/21_web_scraping.md",
    "python/21.1_exercices.md",
    "python/20_classes_and_objects.md",
    "python/20.1_exercices.md",
    "python/19.2_creating_a_packages",
    "python/17.3_characters_above.png",
    "basics_python/17.3_characters_above.png",
    "newstaff/17.3_characters_above.png",
    "Sin título.canvas"
  ]
}